MANIFEST.in
README.md
requirements.txt
setup.py
steamapi/__init__.py
steamapi/app.py
steamapi/consts.py
steamapi/core.py
steamapi/decorators.py
steamapi/errors.py
steamapi/store.py
steamapi/user.py
steamapi_aagallag.egg-info/PKG-INFO
steamapi_aagallag.egg-info/SOURCES.txt
steamapi_aagallag.egg-info/dependency_links.txt
steamapi_aagallag.egg-info/not-zip-safe
steamapi_aagallag.egg-info/requires.txt
steamapi_aagallag.egg-info/top_level.txt