Metadata-Version: 1.0
Name: steamapi-aagallag
Version: 0.1.1
Summary: An object-oriented Python 2.7+ library for accessing the Steam Web API
Home-page: https://github.com/aagallag/steamapi
Author: Smiley
Author-email: UNKNOWN
License: MIT
Platform: UNKNOWN
